pyrps/__init__.py
pyrps/data_hdlr.py
pyrps/rps.py
pyrockpaperscissors-1.0.2.dist-info/METADATA
pyrockpaperscissors-1.0.2.dist-info/WHEEL
pyrockpaperscissors-1.0.2.dist-info/entry_points.txt
pyrockpaperscissors-1.0.2.dist-info/top_level.txt
pyrockpaperscissors-1.0.2.dist-info/RECORD
