Metadata-Version: 2.1
Name: pyrockpaperscissors
Version: 1.0.2
Summary: A simple Rock Paper Scissors Game written in Python🐍
